_MOM/App_Type.py
_MOM/Babel.py
_MOM/Command.py
_MOM/DB_Man.py
_MOM/DB_Meta_Data.py
_MOM/Derived_PNS.py
_MOM/Document.py
_MOM/E_Type_Manager.py
_MOM/Entity.py
_MOM/Error.py
_MOM/Id_Entity_has_Tag.py
_MOM/Inspect.py
_MOM/LICENSE
_MOM/Legacy_Lifter.py
_MOM/Link.py
_MOM/Object.py
_MOM/Product_Version.py
_MOM/Q_Exp.py
_MOM/README.rst
_MOM/SQ.py
_MOM/Scope.py
_MOM/Selector.py
_MOM/UI_Spec.py
_MOM/VERSION.py
_MOM/__babel__.py
_MOM/__doc__.py
_MOM/__init__.py
_MOM/__test__.py
_MOM/babel.cfg
_MOM/base_babel.cfg
_MOM/formatted.py
_MOM/graph.py
_MOM/import_MOM.py
_MOM/setup.cfg
_MOM/setup.py
_MOM/sphinx_autodoc.py
_MOM/-I18N/de.po
_MOM/-I18N/en.po
_MOM/-I18N/pt.po
_MOM/-I18N/template.pot
_MOM/_Attr/A_2D.py
_MOM/_Attr/Coll.py
_MOM/_Attr/Completer.py
_MOM/_Attr/Date_Delta_Interval.py
_MOM/_Attr/Date_Interval.py
_MOM/_Attr/Date_Time.py
_MOM/_Attr/Date_Time_Delta.py
_MOM/_Attr/Date_Time_Interval.py
_MOM/_Attr/Filter.py
_MOM/_Attr/Kind.py
_MOM/_Attr/Manager.py
_MOM/_Attr/Number_Interval.py
_MOM/_Attr/Polisher.py
_MOM/_Attr/Position.py
_MOM/_Attr/Querier.py
_MOM/_Attr/Range.py
_MOM/_Attr/Range_DT.py
_MOM/_Attr/Recurrence_Rule.py
_MOM/_Attr/Selector.py
_MOM/_Attr/Spec.py
_MOM/_Attr/Structured.py
_MOM/_Attr/Time_Delta.py
_MOM/_Attr/Time_Interval.py
_MOM/_Attr/Type.py
_MOM/_Attr/__init__.py
_MOM/_DBW/Pid_Manager.py
_MOM/_DBW/_DBS_.py
_MOM/_DBW/_Manager_.py
_MOM/_DBW/__init__.py
_MOM/_DBW/_HPS/Change_Manager.py
_MOM/_DBW/_HPS/DBS.py
_MOM/_DBW/_HPS/Manager.py
_MOM/_DBW/_HPS/Pid_Manager.py
_MOM/_DBW/_HPS/Store.py
_MOM/_DBW/_HPS/__init__.py
_MOM/_DBW/_SAW/Attr.py
_MOM/_DBW/_SAW/Attr__Range.py
_MOM/_DBW/_SAW/DBS.py
_MOM/_DBW/_SAW/E_Type_Wrapper.py
_MOM/_DBW/_SAW/Manager.py
_MOM/_DBW/_SAW/Pid_Manager.py
_MOM/_DBW/_SAW/QX.py
_MOM/_DBW/_SAW/Q_Result.py
_MOM/_DBW/_SAW/SA.py
_MOM/_DBW/_SAW/SA_Type.py
_MOM/_DBW/_SAW/Sequence.py
_MOM/_DBW/_SAW/Session.py
_MOM/_DBW/_SAW/__init__.py
_MOM/_DBW/_SAW/_MY/DBS.py
_MOM/_DBW/_SAW/_MY/E_Type_Wrapper.py
_MOM/_DBW/_SAW/_MY/Manager.py
MOM_Tapyr-3.9.dist-info/LICENSE
MOM_Tapyr-3.9.dist-info/METADATA
MOM_Tapyr-3.9.dist-info/WHEEL
MOM_Tapyr-3.9.dist-info/top_level.txt
MOM_Tapyr-3.9.dist-info/RECORD
