Metadata-Version: 2.1
Name: MOM-Tapyr
Version: 3.9
Summary: Framework for the implementation of essential object models.
Home-page: https://codeberg.org/tanzer/tapyr
Author: Christian Tanzer
Author-email: tanzer@swing.co.at
License: BSD License
Platform: Any
Classifier: Development Status :: 5 - Production/Stable
Classifier: License :: OSI Approved :: BSD License
Classifier: Operating System :: OS Independent
Classifier: Programming Language :: Python
Classifier: Intended Audience :: Developers
Classifier: Topic :: Software Development :: Libraries :: Python Modules
Requires-Python: >=3.9
License-File: LICENSE
Requires-Dist: TFL (>=3)
Requires-Dist: CAL (>=3)
Requires-Dist: babel
Requires-Dist: python-dateutil
Requires-Dist: sqlalchemy
Provides-Extra: bcrypt
Requires-Dist: bcrypt ; extra == 'bcrypt'
Provides-Extra: deploy
Requires-Dist: plumbum ; extra == 'deploy'
Provides-Extra: doc
Requires-Dist: plumbum ; extra == 'doc'
Requires-Dist: sphinx ; extra == 'doc'
Provides-Extra: postgresql
Requires-Dist: psycopg2 ; extra == 'postgresql'
